fds/__init__.py
fds/sdk/__init__.py
fds/sdk/FactSetEntityReportBuilder/__init__.py
fds/sdk/FactSetEntityReportBuilder/api_client.py
fds/sdk/FactSetEntityReportBuilder/configuration.py
fds/sdk/FactSetEntityReportBuilder/exceptions.py
fds/sdk/FactSetEntityReportBuilder/model_utils.py
fds/sdk/FactSetEntityReportBuilder/rest.py
fds/sdk/FactSetEntityReportBuilder/api/__init__.py
fds/sdk/FactSetEntityReportBuilder/api/entity_structure_api.py
fds/sdk/FactSetEntityReportBuilder/apis/__init__.py
fds/sdk/FactSetEntityReportBuilder/model/__init__.py
fds/sdk/FactSetEntityReportBuilder/model/error_object.py
fds/sdk/FactSetEntityReportBuilder/model/error_object_links.py
fds/sdk/FactSetEntityReportBuilder/model/error_object_source.py
fds/sdk/FactSetEntityReportBuilder/model/error_response.py
fds/sdk/FactSetEntityReportBuilder/model/meta.py
fds/sdk/FactSetEntityReportBuilder/model/response.py
fds/sdk/FactSetEntityReportBuilder/models/__init__.py
fds.sdk.FactSetEntityReportBuilder-1.0.14.dist-info/LICENSE
fds.sdk.FactSetEntityReportBuilder-1.0.14.dist-info/METADATA
fds.sdk.FactSetEntityReportBuilder-1.0.14.dist-info/WHEEL
fds.sdk.FactSetEntityReportBuilder-1.0.14.dist-info/top_level.txt
fds.sdk.FactSetEntityReportBuilder-1.0.14.dist-info/RECORD
